sample/__init__.py
sample/core.py
sample/helpers.py
supertestproject-0.1.0.dist-info/LICENSE
supertestproject-0.1.0.dist-info/METADATA
supertestproject-0.1.0.dist-info/WHEEL
supertestproject-0.1.0.dist-info/top_level.txt
supertestproject-0.1.0.dist-info/RECORD
