Metadata-Version: 2.1
Name: supertestproject
Version: 0.1.0
Summary: Sample package for Python-Guide.org
Home-page: https://github.com/glazyrinae
Author: Kenneth Reitz
Author-email: me@kennethreitz.com
License: Copyright (c) 2017, Kenneth Reitz
